Metadata-Version: 2.4
Name: moana-astro
Version: 0.3.0
Summary: MOAna: Microlensing Observations ANAlysis tools
Project-URL: Homepage, https://github.com/clementranc/moana
Author: Clément Ranc, Stela Ishitani Silva, Greg Olmschenk, MOAna authors
Author-email: ranc@iap.fr
License-Expression: MIT
License-File: AUTHORS.rst
License-File: LICENSE
Requires-Python: >=3.10
Requires-Dist: matplotlib>=3.8.4
Requires-Dist: pandas>=2.1.4
Requires-Dist: scipy>=1.14.1
